docs/CLI.md
docs/INSTALLATION_FRAMEWORK.md
docs/PUBLISHING.md
docs/README.md
docs/SUMMARY.md
docs/01-getting-started/configuration.md
docs/01-getting-started/installation.md
docs/01-getting-started/project-structure.md
docs/01-getting-started/quickstart.md
docs/01-getting-started/templates.md
docs/02-backend/api-routing.md
docs/02-backend/architecture.md
docs/02-backend/authentication.md
docs/02-backend/database.md
docs/02-backend/events.md
docs/02-backend/integrations.md
docs/02-backend/redis-cache.md
docs/02-backend/tasks-jobs.md
docs/03-frontend/architecture.md
docs/03-frontend/hooks-utils.md
docs/03-frontend/routing.md
docs/03-frontend/state-management.md
docs/03-frontend/styling-theme.md
docs/03-frontend/ui-kit.md
docs/04-ui-kit/advanced-components.md
docs/04-ui-kit/basic-components.md
docs/04-ui-kit/form-components.md
docs/04-ui-kit/introduction.md
docs/04-ui-kit/theme-customization.md
docs/05-modules/authentication.md
docs/05-modules/billing.md
docs/05-modules/file-management.md
docs/05-modules/notifications.md
docs/05-modules/user-management.md
docs/06-examples/advanced-examples.md
docs/06-examples/basic-examples.md
docs/06-examples/integration-examples.md
docs/07-development/debugging.md
docs/07-development/development-guide.md
docs/07-development/performance.md
docs/07-development/testing.md
docs/08-deployment/cicd.md
docs/08-deployment/deployment.md
docs/08-deployment/docker.md
docs/09-api-reference/authentication.md
docs/09-api-reference/billing.md
docs/09-api-reference/overview.md
docs/09-api-reference/user-management.md
scripts/update_version.py
services/postgres/docker-compose.yml
services/redis/docker-compose.yml
src/__init__.py
src/init_db.py
src/_scripts/database_backup_solution.py
src/_scripts/db_monitor.py
src/_scripts/redis_monitor.py
src/api/__init__.py
src/api/admin_api.py
src/api/app.py
src/api/auth_api.py
src/api/billing_api.py
src/api/notifications_api.py
src/cli/__init__.py
src/cli/commands.py
src/cli/main.py
src/cli/templates/__init__.py
wework_framework-1.1.2.dist-info/licenses/LICENSE
wework_framework-1.1.2.dist-info/METADATA
wework_framework-1.1.2.dist-info/WHEEL
wework_framework-1.1.2.dist-info/entry_points.txt
wework_framework-1.1.2.dist-info/top_level.txt
wework_framework-1.1.2.dist-info/RECORD
