Metadata-Version: 2.4
Name: wework-framework
Version: 1.1.2
Summary: A modular full-stack framework for building modern web applications
Home-page: https://github.com/wecanco/WeWork
Author: WeCanCo Team
Author-email: WeWork Team <info@wework.dev>
License: MIT
Project-URL: Documentation, https://github.com/wecanco/WeWork/docs
Project-URL: Source, https://github.com/wecanco/WeWork
Project-URL: Tracker, https://github.com/wecanco/WeWork/issues
Keywords: framework,fastapi,react,fullstack,web,development
Classifier: Development Status :: 4 - Beta
Classifier: Intended Audience :: Developers
Classifier: License :: OSI Approved :: MIT License
Classifier: Programming Language :: Python :: 3
Classifier: Programming Language :: Python :: 3.9
Classifier: Programming Language :: Python :: 3.10
Classifier: Programming Language :: Python :: 3.11
Classifier: Programming Language :: Python :: 3.12
Classifier: Framework :: FastAPI
Classifier: Topic :: Software Development :: Libraries :: Application Frameworks
Requires-Python: >=3.9
License-File: LICENSE
Requires-Dist: sqlalchemy[asyncio]>=1.4
Requires-Dist: asyncpg>=0.27
Requires-Dist: alembic>=1.10
Requires-Dist: pydantic>=1.10
Requires-Dist: python-dotenv
Requires-Dist: httpx
Requires-Dist: fastapi
Requires-Dist: uvicorn[standard]
Requires-Dist: pywebpush>=1.9.0
Requires-Dist: redis>=4.5
Requires-Dist: passlib[bcrypt]
Requires-Dist: python-jose[cryptography]
Requires-Dist: pydantic[email]
Requires-Dist: python-multipart
Requires-Dist: click>=8.0.0
Provides-Extra: dev
Requires-Dist: pytest; extra == "dev"
Dynamic: author
Dynamic: home-page
Dynamic: license-file
Dynamic: requires-python
